transfer/__init__.py
transfer/transfer.py
extremegohorse-0.1.1.dist-info/LICENSE
extremegohorse-0.1.1.dist-info/METADATA
extremegohorse-0.1.1.dist-info/WHEEL
extremegohorse-0.1.1.dist-info/top_level.txt
extremegohorse-0.1.1.dist-info/RECORD
